{"DataList": [{"type": "Point", "id": 1, "coordinates": [356.7902, 753.5822000000001], "properties": "VisiblePoint"}, {"type": "Point", "id": 2, "coordinates": [413.2902, 705.0822000000001], "properties": "VisiblePoint"}, {"type": "Point", "id": 3, "coordinates": [436.2902, 685.5822000000001], "properties": "VisiblePoint"}, {"type": "Point", "id": 4, "coordinates": [465.2902, 694.5822000000001], "properties": "VisiblePoint"}, {"type": "Point", "id": 5, "coordinates": [469.7902, 724.5822000000001], "properties": "InvisiblePoint"}, {"type": "Point", "id": 6, "coordinates": [465.7902, 730.5822000000001], "properties": "VisiblePoint"}, {"type": "Point", "id": 7, "coordinates": [523.2902, 724.0822000000001], "properties": "VisiblePoint"}, {"type": "Point", "id": 8, "coordinates": [562.7902, 718.5822000000001], "properties": "VisiblePoint"}, {"type": "Point", "id": 9, "coordinates": [594.7902, 717.0822000000001], "properties": "VisiblePoint"}, {"type": "Point", "id": 10, "coordinates": [477.7902, 754.0822000000001], "properties": "VisiblePoint"}, {"type": "Point", "id": 11, "coordinates": [494.7902, 729.0822000000001], "properties": "InvisiblePoint"}, {"type": "Point", "id": 12, "coordinates": [471.7902, 732.0822000000001], "properties": "InvisiblePoint"}, {"type": "Point", "id": 13, "coordinates": [452.2902, 739.0822000000001], "properties": "InvisiblePoint"}, {"type": "Point", "id": 14, "coordinates": [467.7902, 780.0822000000001], "properties": "VisiblePoint"}, {"type": "Point", "id": 15, "coordinates": [488.2902, 750.0822000000001], "properties": "InvisiblePoint"}, {"type": "Point", "id": 16, "coordinates": [464.2902, 754.5822000000001], "properties": "InvisiblePoint"}, {"type": "Point", "id": 17, "coordinates": [448.89420000000007, 761.5086], "properties": "InvisiblePoint"}, {"type": "Point", "id": 18, "coordinates": [464.2902, 792.5822000000001], "properties": "VisiblePoint"}, {"type": "Point", "id": 19, "coordinates": [494.2902, 783.0822000000001], "properties": "VisiblePoint"}, {"type": "Point", "id": 20, "coordinates": [523.7902, 778.5822000000001], "properties": "VisiblePoint"}, {"type": "Point", "id": 21, "coordinates": [543.7902, 778.0822000000001], "properties": "VisiblePoint"}], "WorkLoad": {"Orientation": "front", "SequenceNumber": "13", "CameraPosition": "center", "Hand": "right", "Background": "outdoor", "Rotation": "90", "Sex": "female"}, "Filepath": "13_00170.jpg"}
