{"DataList": [{"type": "Point", "id": 1, "coordinates": [284.79139999999995, 965.6989999999997], "properties": "VisiblePoint"}, {"type": "Point", "id": 2, "coordinates": [250.29139999999995, 868.1989999999997], "properties": "VisiblePoint"}, {"type": "Point", "id": 3, "coordinates": [259.79139999999995, 821.1989999999997], "properties": "InvisiblePoint"}, {"type": "Point", "id": 4, "coordinates": [295.79139999999995, 779.6989999999997], "properties": "VisiblePoint"}, {"type": "Point", "id": 5, "coordinates": [326.79139999999995, 791.6989999999997], "properties": "InvisiblePoint"}, {"type": "Point", "id": 6, "coordinates": [269.29139999999995, 854.1989999999997], "properties": "VisiblePoint"}, {"type": "Point", "id": 7, "coordinates": [261.79139999999995, 778.1989999999997], "properties": "VisiblePoint"}, {"type": "Point", "id": 8, "coordinates": [255.79139999999995, 726.6989999999997], "properties": "VisiblePoint"}, {"type": "Point", "id": 9, "coordinates": [251.29139999999995, 690.1989999999997], "properties": "VisiblePoint"}, {"type": "Point", "id": 10, "coordinates": [310.79139999999995, 841.1989999999997], "properties": "VisiblePoint"}, {"type": "Point", "id": 11, "coordinates": [324.29139999999995, 761.6989999999997], "properties": "VisiblePoint"}, {"type": "Point", "id": 12, "coordinates": [310.29139999999995, 783.1989999999997], "properties": "InvisiblePoint"}, {"type": "Point", "id": 13, "coordinates": [299.29139999999995, 811.6989999999997], "properties": "InvisiblePoint"}, {"type": "Point", "id": 14, "coordinates": [337.69220000000007, 856.5550000000001], "properties": "VisiblePoint"}, {"type": "Point", "id": 15, "coordinates": [355.29139999999995, 782.1989999999997], "properties": "VisiblePoint"}, {"type": "Point", "id": 16, "coordinates": [342.79139999999995, 801.1989999999997], "properties": "InvisiblePoint"}, {"type": "Point", "id": 17, "coordinates": [332.29139999999995, 832.6989999999997], "properties": "InvisiblePoint"}, {"type": "Point", "id": 18, "coordinates": [365.79139999999995, 867.1989999999997], "properties": "VisiblePoint"}, {"type": "Point", "id": 19, "coordinates": [409.29139999999995, 815.6989999999997], "properties": "VisiblePoint"}, {"type": "Point", "id": 20, "coordinates": [435.79139999999995, 797.6989999999997], "properties": "VisiblePoint"}, {"type": "Point", "id": 21, "coordinates": [460.79139999999995, 774.1989999999997], "properties": "VisiblePoint"}], "WorkLoad": {"Orientation": "front", "SequenceNumber": "13", "CameraPosition": "up", "Hand": "right", "Background": "outdoor", "Rotation": "0", "Sex": "female"}, "Filepath": "13_00006.jpg"}
