{"DataList": [{"type": "Point", "id": 1, "coordinates": [527.9922, 679.3290000000001], "properties": "InvisiblePoint"}, {"type": "Point", "id": 2, "coordinates": [577.4922, 603.3290000000001], "properties": "VisiblePoint"}, {"type": "Point", "id": 3, "coordinates": [587.4922, 567.8290000000001], "properties": "VisiblePoint"}, {"type": "Point", "id": 4, "coordinates": [596.9922, 534.3290000000001], "properties": "InvisiblePoint"}, {"type": "Point", "id": 5, "coordinates": [611.4922, 508.32900000000006], "properties": "VisiblePoint"}, {"type": "Point", "id": 6, "coordinates": [540.4922, 515.8290000000001], "properties": "InvisiblePoint"}, {"type": "Point", "id": 7, "coordinates": [558.9922, 423.82900000000006], "properties": "InvisiblePoint"}, {"type": "Point", "id": 8, "coordinates": [567.9922, 376.82900000000006], "properties": "InvisiblePoint"}, {"type": "Point", "id": 9, "coordinates": [576.4922, 337.82900000000006], "properties": "InvisiblePoint"}, {"type": "Point", "id": 10, "coordinates": [522.9922, 536.3290000000001], "properties": "InvisiblePoint"}, {"type": "Point", "id": 11, "coordinates": [541.4922, 427.82900000000006], "properties": "VisiblePoint"}, {"type": "Point", "id": 12, "coordinates": [556.4922, 376.82900000000006], "properties": "VisiblePoint"}, {"type": "Point", "id": 13, "coordinates": [568.9922, 322.82900000000006], "properties": "VisiblePoint"}, {"type": "Point", "id": 14, "coordinates": [501.9922, 552.8290000000001], "properties": "VisiblePoint"}, {"type": "Point", "id": 15, "coordinates": [537.4922, 467.82900000000006], "properties": "VisiblePoint"}, {"type": "Point", "id": 16, "coordinates": [587.9922, 502.32900000000006], "properties": "VisiblePoint"}, {"type": "Point", "id": 17, "coordinates": [589.4922, 539.8290000000001], "properties": "InvisiblePoint"}, {"type": "Point", "id": 18, "coordinates": [539.9922, 572.8290000000001], "properties": "VisiblePoint"}, {"type": "Point", "id": 19, "coordinates": [561.4922, 518.8290000000001], "properties": "VisiblePoint"}, {"type": "Point", "id": 20, "coordinates": [596.9922, 533.8290000000001], "properties": "VisiblePoint"}, {"type": "Point", "id": 21, "coordinates": [597.9922, 554.8290000000001], "properties": "VisiblePoint"}], "WorkLoad": {"Orientation": "front", "SequenceNumber": "2", "CameraPosition": "left", "Hand": "right", "Background": "outdoor", "Rotation": "0", "Sex": "female"}, "Filepath": "2_00233.jpg"}
