{"DataList": [{"type": "Point", "id": 1, "coordinates": [570.7454, 903.1006], "properties": "VisiblePoint"}, {"type": "Point", "id": 2, "coordinates": [608.7454, 867.1006], "properties": "VisiblePoint"}, {"type": "Point", "id": 3, "coordinates": [645.2454, 840.6006], "properties": "VisiblePoint"}, {"type": "Point", "id": 4, "coordinates": [684.4954, 811.1006], "properties": "VisiblePoint"}, {"type": "Point", "id": 5, "coordinates": [695.3704, 787.7256], "properties": "VisiblePoint"}, {"type": "Point", "id": 6, "coordinates": [597.3704, 792.9756], "properties": "VisiblePoint"}, {"type": "Point", "id": 7, "coordinates": [604.8704, 716.9756], "properties": "VisiblePoint"}, {"type": "Point", "id": 8, "coordinates": [606.8704, 682.4756], "properties": "VisiblePoint"}, {"type": "Point", "id": 9, "coordinates": [605.3704, 643.7256], "properties": "VisiblePoint"}, {"type": "Point", "id": 10, "coordinates": [592.6204, 777.4756], "properties": "InvisiblePoint"}, {"type": "Point", "id": 11, "coordinates": [625.6204, 699.4756], "properties": "VisiblePoint"}, {"type": "Point", "id": 12, "coordinates": [630.3704, 665.7256], "properties": "VisiblePoint"}, {"type": "Point", "id": 13, "coordinates": [626.8704, 634.4756], "properties": "VisiblePoint"}, {"type": "Point", "id": 14, "coordinates": [589.7454, 771.8506], "properties": "InvisiblePoint"}, {"type": "Point", "id": 15, "coordinates": [642.2454, 743.6006], "properties": "VisiblePoint"}, {"type": "Point", "id": 16, "coordinates": [670.9954, 772.3506], "properties": "VisiblePoint"}, {"type": "Point", "id": 17, "coordinates": [663.9954, 799.8506], "properties": "VisiblePoint"}, {"type": "Point", "id": 18, "coordinates": [602.7454, 779.9756], "properties": "InvisiblePoint"}, {"type": "Point", "id": 19, "coordinates": [633.2454, 781.7256], "properties": "VisiblePoint"}, {"type": "Point", "id": 20, "coordinates": [651.7454, 793.2256], "properties": "VisiblePoint"}, {"type": "Point", "id": 21, "coordinates": [659.4954, 813.7256], "properties": "InvisiblePoint"}], "WorkLoad": {"Orientation": "front", "SequenceNumber": "2", "CameraPosition": "left", "Hand": "left", "Background": "outdoor", "Rotation": "0", "Sex": "female"}, "Filepath": "2_00074.jpg"}
