{"DataList": [{"type": "Point", "id": 1, "coordinates": [612.5878, 787.2854], "properties": "VisiblePoint"}, {"type": "Point", "id": 2, "coordinates": [531.8378, 773.2854], "properties": "VisiblePoint"}, {"type": "Point", "id": 3, "coordinates": [495.3378, 766.0354], "properties": "VisiblePoint"}, {"type": "Point", "id": 4, "coordinates": [460.5878, 726.5354], "properties": "VisiblePoint"}, {"type": "Point", "id": 5, "coordinates": [484.5878, 687.0354], "properties": "VisiblePoint"}, {"type": "Point", "id": 6, "coordinates": [468.5878, 681.2854], "properties": "VisiblePoint"}, {"type": "Point", "id": 7, "coordinates": [392.8378, 632.2854], "properties": "VisiblePoint"}, {"type": "Point", "id": 8, "coordinates": [369.3378, 611.5354], "properties": "VisiblePoint"}, {"type": "Point", "id": 9, "coordinates": [343.8378, 584.0354], "properties": "VisiblePoint"}, {"type": "Point", "id": 10, "coordinates": [492.0878, 665.2854], "properties": "InvisiblePoint"}, {"type": "Point", "id": 11, "coordinates": [455.3378, 580.7854], "properties": "VisiblePoint"}, {"type": "Point", "id": 12, "coordinates": [433.8378, 543.5354], "properties": "VisiblePoint"}, {"type": "Point", "id": 13, "coordinates": [415.2128, 502.7854], "properties": "VisiblePoint"}, {"type": "Point", "id": 14, "coordinates": [546.9326000000001, 656.3474], "properties": "InvisiblePoint"}, {"type": "Point", "id": 15, "coordinates": [496.8378, 644.5354], "properties": "VisiblePoint"}, {"type": "Point", "id": 16, "coordinates": [503.8378, 698.7854], "properties": "VisiblePoint"}, {"type": "Point", "id": 17, "coordinates": [514.5878, 743.5354], "properties": "VisiblePoint"}, {"type": "Point", "id": 18, "coordinates": [568.9326000000001, 663.3474], "properties": "VisiblePoint"}, {"type": "Point", "id": 19, "coordinates": [549.3378, 670.5354], "properties": "VisiblePoint"}, {"type": "Point", "id": 20, "coordinates": [546.3378, 710.0354], "properties": "VisiblePoint"}, {"type": "Point", "id": 21, "coordinates": [549.0878, 744.5354], "properties": "VisiblePoint"}], "WorkLoad": {"Orientation": "front", "SequenceNumber": "2", "CameraPosition": "center", "Hand": "left", "Background": "outdoor", "Rotation": "45", "Sex": "female"}, "Filepath": "2_00172.jpg"}
