{"DataList": [{"type": "Point", "id": 1, "coordinates": [198.56740000000002, 859.5237999999999], "properties": "InvisiblePoint"}, {"type": "Point", "id": 2, "coordinates": [240.6282000000001, 858.8797999999999], "properties": "InvisiblePoint"}, {"type": "Point", "id": 3, "coordinates": [286.6282000000001, 835.5047999999999], "properties": "VisiblePoint"}, {"type": "Point", "id": 4, "coordinates": [256.0032000000001, 875.7547999999999], "properties": "VisiblePoint"}, {"type": "Point", "id": 5, "coordinates": [216.7532000000001, 884.5047999999999], "properties": "VisiblePoint"}, {"type": "Point", "id": 6, "coordinates": [254.5032000000001, 771.2547999999999], "properties": "VisiblePoint"}, {"type": "Point", "id": 7, "coordinates": [278.0032000000001, 689.0047999999999], "properties": "VisiblePoint"}, {"type": "Point", "id": 8, "coordinates": [289.0032000000001, 651.7547999999999], "properties": "VisiblePoint"}, {"type": "Point", "id": 9, "coordinates": [302.2532000000001, 595.2547999999999], "properties": "VisiblePoint"}, {"type": "Point", "id": 10, "coordinates": [213.5032000000001, 779.2547999999999], "properties": "VisiblePoint"}, {"type": "Point", "id": 11, "coordinates": [184.0032000000001, 697.2547999999999], "properties": "VisiblePoint"}, {"type": "Point", "id": 12, "coordinates": [170.0032000000001, 653.7547999999999], "properties": "VisiblePoint"}, {"type": "Point", "id": 13, "coordinates": [146.2532000000001, 600.7547999999999], "properties": "VisiblePoint"}, {"type": "Point", "id": 14, "coordinates": [191.7532000000001, 797.7547999999999], "properties": "VisiblePoint"}, {"type": "Point", "id": 15, "coordinates": [147.5032000000001, 779.7547999999999], "properties": "VisiblePoint"}, {"type": "Point", "id": 16, "coordinates": [177.5032000000001, 841.7547999999999], "properties": "VisiblePoint"}, {"type": "Point", "id": 17, "coordinates": [216.2532000000001, 886.3797999999999], "properties": "InvisiblePoint"}, {"type": "Point", "id": 18, "coordinates": [131.3782000000001, 805.1297999999999], "properties": "VisiblePoint"}, {"type": "Point", "id": 19, "coordinates": [151.6282000000001, 852.3797999999999], "properties": "VisiblePoint"}, {"type": "Point", "id": 20, "coordinates": [173.8782000000001, 879.3797999999999], "properties": "VisiblePoint"}, {"type": "Point", "id": 21, "coordinates": [207.8782000000001, 920.3797999999999], "properties": "VisiblePoint"}], "WorkLoad": {"Orientation": "front", "SequenceNumber": "2", "CameraPosition": "up", "Hand": "right", "Background": "outdoor", "Rotation": "0", "Sex": "female"}, "Filepath": "2_00275.jpg"}
