{"DataList": [{"type": "Point", "id": 1, "coordinates": [164.9226, 843.1346], "properties": "VisiblePoint"}, {"type": "Point", "id": 2, "coordinates": [199.9226, 795.6346], "properties": "VisiblePoint"}, {"type": "Point", "id": 3, "coordinates": [208.4226, 752.6346], "properties": "VisiblePoint"}, {"type": "Point", "id": 4, "coordinates": [169.9226, 712.6346], "properties": "VisiblePoint"}, {"type": "Point", "id": 5, "coordinates": [105.92259999999999, 702.6346], "properties": "VisiblePoint"}, {"type": "Point", "id": 6, "coordinates": [195.4226, 677.6346], "properties": "VisiblePoint"}, {"type": "Point", "id": 7, "coordinates": [220.9226, 593.6346], "properties": "VisiblePoint"}, {"type": "Point", "id": 8, "coordinates": [232.9226, 552.1346], "properties": "VisiblePoint"}, {"type": "Point", "id": 9, "coordinates": [247.4226, 504.6346], "properties": "VisiblePoint"}, {"type": "Point", "id": 10, "coordinates": [154.9226, 672.6346], "properties": "VisiblePoint"}, {"type": "Point", "id": 11, "coordinates": [153.4226, 580.6346], "properties": "VisiblePoint"}, {"type": "Point", "id": 12, "coordinates": [149.9226, 532.6346], "properties": "VisiblePoint"}, {"type": "Point", "id": 13, "coordinates": [147.4226, 489.1346], "properties": "VisiblePoint"}, {"type": "Point", "id": 14, "coordinates": [132.4226, 684.6346], "properties": "VisiblePoint"}, {"type": "Point", "id": 15, "coordinates": [102.42259999999999, 615.6346], "properties": "VisiblePoint"}, {"type": "Point", "id": 16, "coordinates": [84.42259999999999, 570.6346], "properties": "VisiblePoint"}, {"type": "Point", "id": 17, "coordinates": [69.42259999999999, 518.6346], "properties": "VisiblePoint"}, {"type": "Point", "id": 18, "coordinates": [98.42259999999999, 730.6346], "properties": "VisiblePoint"}, {"type": "Point", "id": 19, "coordinates": [96.42259999999999, 677.1346], "properties": "VisiblePoint"}, {"type": "Point", "id": 20, "coordinates": [118.92259999999999, 705.6346], "properties": "InvisiblePoint"}, {"type": "Point", "id": 21, "coordinates": [127.42259999999999, 744.1346], "properties": "VisiblePoint"}], "WorkLoad": {"Orientation": "front", "SequenceNumber": "3", "CameraPosition": "center", "Hand": "right", "Background": "outdoor", "Rotation": "0", "Sex": "female"}, "Filepath": "3_00097.jpg"}
