{"DataList": [{"type": "Point", "id": 1, "coordinates": [202.52100000000007, 847.8646], "properties": "VisiblePoint"}, {"type": "Point", "id": 2, "coordinates": [252.35940000000005, 811.957], "properties": "VisiblePoint"}, {"type": "Point", "id": 3, "coordinates": [291.35940000000005, 781.957], "properties": "VisiblePoint"}, {"type": "Point", "id": 4, "coordinates": [294.85940000000005, 726.957], "properties": "VisiblePoint"}, {"type": "Point", "id": 5, "coordinates": [256.85940000000005, 692.957], "properties": "VisiblePoint"}, {"type": "Point", "id": 6, "coordinates": [297.35940000000005, 708.957], "properties": "VisiblePoint"}, {"type": "Point", "id": 7, "coordinates": [337.35940000000005, 648.457], "properties": "VisiblePoint"}, {"type": "Point", "id": 8, "coordinates": [355.85940000000005, 616.957], "properties": "VisiblePoint"}, {"type": "Point", "id": 9, "coordinates": [366.85940000000005, 584.957], "properties": "VisiblePoint"}, {"type": "Point", "id": 10, "coordinates": [269.60940000000005, 698.957], "properties": "InvisiblePoint"}, {"type": "Point", "id": 11, "coordinates": [283.10940000000005, 623.457], "properties": "VisiblePoint"}, {"type": "Point", "id": 12, "coordinates": [290.35940000000005, 575.707], "properties": "VisiblePoint"}, {"type": "Point", "id": 13, "coordinates": [291.85940000000005, 536.957], "properties": "VisiblePoint"}, {"type": "Point", "id": 14, "coordinates": [237.60940000000005, 703.957], "properties": "InvisiblePoint"}, {"type": "Point", "id": 15, "coordinates": [248.35940000000005, 636.707], "properties": "VisiblePoint"}, {"type": "Point", "id": 16, "coordinates": [256.35940000000005, 589.707], "properties": "VisiblePoint"}, {"type": "Point", "id": 17, "coordinates": [258.60940000000005, 548.957], "properties": "VisiblePoint"}, {"type": "Point", "id": 18, "coordinates": [193.35940000000005, 716.957], "properties": "VisiblePoint"}, {"type": "Point", "id": 19, "coordinates": [233.60940000000005, 672.707], "properties": "VisiblePoint"}, {"type": "Point", "id": 20, "coordinates": [250.35940000000005, 700.457], "properties": "InvisiblePoint"}, {"type": "Point", "id": 21, "coordinates": [248.35940000000005, 732.957], "properties": "VisiblePoint"}], "WorkLoad": {"Orientation": "front", "SequenceNumber": "3", "CameraPosition": "center", "Hand": "right", "Background": "outdoor", "Rotation": "30", "Sex": "female"}, "Filepath": "3_00210.jpg"}
