{"DataList": [{"type": "Point", "id": 1, "coordinates": [185.30460000000005, 909.9838000000001], "properties": "VisiblePoint"}, {"type": "Point", "id": 2, "coordinates": [243.06860000000006, 842.9861999999995], "properties": "VisiblePoint"}, {"type": "Point", "id": 3, "coordinates": [245.06860000000006, 804.9861999999995], "properties": "VisiblePoint"}, {"type": "Point", "id": 4, "coordinates": [199.06860000000006, 762.9861999999995], "properties": "VisiblePoint"}, {"type": "Point", "id": 5, "coordinates": [147.06860000000006, 742.9861999999995], "properties": "VisiblePoint"}, {"type": "Point", "id": 6, "coordinates": [222.06860000000006, 735.9861999999995], "properties": "VisiblePoint"}, {"type": "Point", "id": 7, "coordinates": [236.06860000000006, 652.9861999999995], "properties": "VisiblePoint"}, {"type": "Point", "id": 8, "coordinates": [242.06860000000006, 616.9861999999995], "properties": "VisiblePoint"}, {"type": "Point", "id": 9, "coordinates": [244.56860000000006, 578.9861999999995], "properties": "VisiblePoint"}, {"type": "Point", "id": 10, "coordinates": [188.56860000000006, 739.4861999999995], "properties": "VisiblePoint"}, {"type": "Point", "id": 11, "coordinates": [165.56860000000006, 655.4861999999995], "properties": "VisiblePoint"}, {"type": "Point", "id": 12, "coordinates": [153.56860000000006, 606.4861999999995], "properties": "VisiblePoint"}, {"type": "Point", "id": 13, "coordinates": [141.06860000000006, 568.9861999999995], "properties": "VisiblePoint"}, {"type": "Point", "id": 14, "coordinates": [161.56860000000003, 764.4861999999995], "properties": "InvisiblePoint"}, {"type": "Point", "id": 15, "coordinates": [127.56860000000003, 682.4861999999995], "properties": "VisiblePoint"}, {"type": "Point", "id": 16, "coordinates": [113.56860000000003, 638.9861999999995], "properties": "VisiblePoint"}, {"type": "Point", "id": 17, "coordinates": [99.56860000000003, 597.4861999999995], "properties": "VisiblePoint"}, {"type": "Point", "id": 18, "coordinates": [130.56860000000003, 787.4861999999995], "properties": "VisiblePoint"}, {"type": "Point", "id": 19, "coordinates": [126.56860000000003, 729.9861999999995], "properties": "VisiblePoint"}, {"type": "Point", "id": 20, "coordinates": [147.06860000000003, 753.4861999999995], "properties": "InvisiblePoint"}, {"type": "Point", "id": 21, "coordinates": [162.06860000000003, 786.4861999999995], "properties": "VisiblePoint"}], "WorkLoad": {"Orientation": "front", "SequenceNumber": "3", "CameraPosition": "center", "Hand": "right", "Background": "outdoor", "Rotation": "0", "Sex": "female"}, "Filepath": "3_00209.jpg"}
