{"DataList": [{"type": "Point", "id": 1, "coordinates": [497.19219999999996, 1090.0038], "properties": "VisiblePoint"}, {"type": "Point", "id": 2, "coordinates": [424.4922, 1075.4486000000002], "properties": "VisiblePoint"}, {"type": "Point", "id": 3, "coordinates": [386.4922, 1057.9486000000002], "properties": "VisiblePoint"}, {"type": "Point", "id": 4, "coordinates": [414.4922, 1042.9486000000002], "properties": "VisiblePoint"}, {"type": "Point", "id": 5, "coordinates": [449.4922, 1024.9486000000002], "properties": "VisiblePoint"}, {"type": "Point", "id": 6, "coordinates": [410.9922, 967.9486], "properties": "VisiblePoint"}, {"type": "Point", "id": 7, "coordinates": [374.9922, 905.9486], "properties": "VisiblePoint"}, {"type": "Point", "id": 8, "coordinates": [359.9922, 869.4486], "properties": "VisiblePoint"}, {"type": "Point", "id": 9, "coordinates": [343.9922, 824.9486], "properties": "VisiblePoint"}, {"type": "Point", "id": 10, "coordinates": [444.4922, 967.9486], "properties": "VisiblePoint"}, {"type": "Point", "id": 11, "coordinates": [439.4922, 887.9486], "properties": "VisiblePoint"}, {"type": "Point", "id": 12, "coordinates": [437.4922, 843.4486], "properties": "VisiblePoint"}, {"type": "Point", "id": 13, "coordinates": [438.4922, 792.9486], "properties": "VisiblePoint"}, {"type": "Point", "id": 14, "coordinates": [464.9922, 979.6986], "properties": "VisiblePoint"}, {"type": "Point", "id": 15, "coordinates": [479.7422, 927.1986], "properties": "VisiblePoint"}, {"type": "Point", "id": 16, "coordinates": [484.9922, 896.4486], "properties": "VisiblePoint"}, {"type": "Point", "id": 17, "coordinates": [489.7422, 849.9486], "properties": "VisiblePoint"}, {"type": "Point", "id": 18, "coordinates": [509.4922, 979.4486], "properties": "VisiblePoint"}, {"type": "Point", "id": 19, "coordinates": [471.9922, 993.1986], "properties": "VisiblePoint"}, {"type": "Point", "id": 20, "coordinates": [454.2422, 1029.4486000000002], "properties": "InvisiblePoint"}, {"type": "Point", "id": 21, "coordinates": [449.9922, 1054.6986000000002], "properties": "VisiblePoint"}], "WorkLoad": {"Orientation": "front", "SequenceNumber": "3", "CameraPosition": "up", "Hand": "left", "Background": "outdoor", "Rotation": "0", "Sex": "female"}, "Filepath": "3_00153.jpg"}
